jav/__init__.py
jav/cli/__init__.py
jav/cli/bootstrap.py
jav/cli/main.py
jav/cli/controllers/__init__.py
jav/cli/controllers/base.py
jav/cli/ext/__init__.py
jav/cli/plugins/__init__.py
jav/cli/templates/__init__.py
jav/core/__init__.py
jav/core/exc.py
jav/core/javBuildChart.py
jav/core/javClear.py
jav/core/javConfig.py
jav/core/javCrunch.py
jav/core/javFiles.py
jav/core/javGithub.py
jav/core/javImportData.py
jav/core/javJira.py
jav/core/javLoad.py
jav/core/javLogConfig.py
jav/core/javMsg.py
jav/core/javPublishGithubPage.py
jav/core/javSetup.py
jav/core/javStatsDay.py
jav/core/javStatsRemaining.py
jav/core/javStatsWeek.py
jav/core/javTime.py
jav/utils/__init__.py
jav/utils/test.py
jav-0.1.2.dist-info/DESCRIPTION.rst
jav-0.1.2.dist-info/METADATA
jav-0.1.2.dist-info/RECORD
jav-0.1.2.dist-info/WHEEL
jav-0.1.2.dist-info/entry_points.txt
jav-0.1.2.dist-info/metadata.json
jav-0.1.2.dist-info/namespace_packages.txt
jav-0.1.2.dist-info/top_level.txt
tests/cli/__init__.py
tests/cli/test_jav.py
tests/cli/ext/__init__.py
tests/cli/plugins/__init__.py
tests/core/__init__.py
tests/core/test_Clear.py
tests/core/test_Config.py
tests/core/test_Time.py
tests/core/test_exc.py
tests/core/test_importData.py
